jupyterlab_zip_extension/__init__.py
jupyterlab_zip_extension/_version.py
jupyterlab_zip_extension/handlers.py
jupyterlab_zip_extension-1.2.5.data/data/etc/jupyter/jupyter_server_config.d/jupyterlab_zip_extension.json
jupyterlab_zip_extension-1.2.5.data/data/share/jupyter/labextensions/jupyterlab_zip_extension/package.json
jupyterlab_zip_extension-1.2.5.data/data/share/jupyter/labextensions/jupyterlab_zip_extension/schemas/jupyterlab_zip_extension/package.json.orig
jupyterlab_zip_extension-1.2.5.data/data/share/jupyter/labextensions/jupyterlab_zip_extension/schemas/jupyterlab_zip_extension/plugin.json
jupyterlab_zip_extension-1.2.5.data/data/share/jupyter/labextensions/jupyterlab_zip_extension/static/675.c076de20c841cea44605.js
jupyterlab_zip_extension-1.2.5.data/data/share/jupyter/labextensions/jupyterlab_zip_extension/static/728.af5fd942762c5c58caed.js
jupyterlab_zip_extension-1.2.5.data/data/share/jupyter/labextensions/jupyterlab_zip_extension/static/remoteEntry.c33b10b23fef4d8686d9.js
jupyterlab_zip_extension-1.2.5.data/data/share/jupyter/labextensions/jupyterlab_zip_extension/static/style.js
jupyterlab_zip_extension-1.2.5.data/data/share/jupyter/labextensions/jupyterlab_zip_extension/static/third-party-licenses.json
jupyterlab_zip_extension-1.2.5.data/data/share/jupyter/labextensions/jupyterlab_zip_extension/install.json
jupyterlab_zip_extension-1.2.5.dist-info/METADATA
jupyterlab_zip_extension-1.2.5.dist-info/WHEEL
jupyterlab_zip_extension-1.2.5.dist-info/licenses/LICENSE
jupyterlab_zip_extension-1.2.5.dist-info/RECORD
